garmy/__init__.py
garmy/py.typed
garmy/auth/__init__.py
garmy/auth/client.py
garmy/auth/exceptions.py
garmy/auth/sso.py
garmy/auth/tokens.py
garmy/core/__init__.py
garmy/core/base.py
garmy/core/client.py
garmy/core/config.py
garmy/core/discovery.py
garmy/core/endpoint_builders.py
garmy/core/exceptions.py
garmy/core/http_client.py
garmy/core/metrics.py
garmy/core/registry.py
garmy/core/utils.py
garmy/localdb/__init__.py
garmy/localdb/__main__.py
garmy/localdb/activities_iterator.py
garmy/localdb/cli.py
garmy/localdb/config.py
garmy/localdb/db.py
garmy/localdb/extractors.py
garmy/localdb/models.py
garmy/localdb/progress.py
garmy/localdb/sync.py
garmy/mcp/__init__.py
garmy/mcp/__main__.py
garmy/mcp/cli.py
garmy/mcp/config.py
garmy/mcp/server.py
garmy/metrics/__init__.py
garmy/metrics/activities.py
garmy/metrics/body_battery.py
garmy/metrics/calories.py
garmy/metrics/daily_summary.py
garmy/metrics/heart_rate.py
garmy/metrics/hrv.py
garmy/metrics/respiration.py
garmy/metrics/sleep.py
garmy/metrics/steps.py
garmy/metrics/stress.py
garmy/metrics/training_readiness.py
garmy-2.0.0.dist-info/licenses/LICENSE
garmy-2.0.0.dist-info/METADATA
garmy-2.0.0.dist-info/WHEEL
garmy-2.0.0.dist-info/entry_points.txt
garmy-2.0.0.dist-info/top_level.txt
garmy-2.0.0.dist-info/RECORD
