Metadata-Version: 2.4
Name: garmy
Version: 2.0.0
Summary: AI-powered Garmin Connect API library for health agents and data analysis
Author-email: bes-dev <sergei.o.belousov@gmail.com>
Maintainer-email: bes-dev <sergei.o.belousov@gmail.com>
License: Apache-2.0
Project-URL: Homepage, https://github.com/bes-dev/garmy
Project-URL: Documentation, https://github.com/bes-dev/garmy/blob/master/docs/
Project-URL: Repository, https://github.com/bes-dev/garmy.git
Project-URL: Bug Tracker, https://github.com/bes-dev/garmy/issues
Project-URL: Changelog, https://github.com/bes-dev/garmy/blob/master/CHANGELOG.md
Keywords: garmin,connect,api,fitness,health,training,metrics,reverse-engineering,lightweight,modular,garth,ai-integration,type-safe,mcp,model-context-protocol,localdb,sqlite
Classifier: Development Status :: 4 - Beta
Classifier: Intended Audience :: Developers
Classifier: Topic :: Software Development :: Libraries :: Python Modules
Classifier: Topic :: Internet :: WWW/HTTP :: Dynamic Content
Classifier: Topic :: Scientific/Engineering :: Information Analysis
Classifier: License :: OSI Approved :: Apache Software License
Classifier: Programming Language :: Python :: 3
Classifier: Programming Language :: Python :: 3.8
Classifier: Programming Language :: Python :: 3.9
Classifier: Programming Language :: Python :: 3.10
Classifier: Programming Language :: Python :: 3.11
Classifier: Programming Language :: Python :: 3.12
Classifier: Operating System :: OS Independent
Classifier: Typing :: Typed
Requires-Python: >=3.8
License-File: LICENSE
Requires-Dist: requests>=2.28.0
Requires-Dist: requests-oauthlib>=1.3.0
Requires-Dist: aiohttp>=3.8.0
Requires-Dist: aiofiles>=22.0.0
Provides-Extra: mcp
Requires-Dist: fastmcp>=0.4.0; extra == "mcp"
Provides-Extra: localdb
Requires-Dist: sqlalchemy>=1.4.0; extra == "localdb"
Requires-Dist: tqdm>=4.0.0; extra == "localdb"
Provides-Extra: all
Requires-Dist: fastmcp>=0.4.0; extra == "all"
Requires-Dist: sqlalchemy>=1.4.0; extra == "all"
Requires-Dist: tqdm>=4.0.0; extra == "all"
Provides-Extra: dev
Requires-Dist: pytest>=7.0.0; extra == "dev"
Requires-Dist: pytest-cov>=4.0.0; extra == "dev"
Requires-Dist: pytest-asyncio>=0.20.0; extra == "dev"
Requires-Dist: black>=22.0.0; extra == "dev"
Requires-Dist: isort>=5.0.0; extra == "dev"
Requires-Dist: mypy>=1.0.0; extra == "dev"
Requires-Dist: types-requests>=2.32.0; extra == "dev"
Requires-Dist: flake8>=5.0.0; extra == "dev"
Requires-Dist: flake8-docstrings>=1.6.0; extra == "dev"
Requires-Dist: flake8-type-checking>=2.4.0; extra == "dev"
Requires-Dist: flake8-bugbear>=23.0.0; extra == "dev"
Requires-Dist: flake8-simplify>=0.20.0; extra == "dev"
Requires-Dist: ruff>=0.1.0; extra == "dev"
Requires-Dist: bandit>=1.7.0; extra == "dev"
Requires-Dist: vulture>=2.7.0; extra == "dev"
Requires-Dist: pre-commit>=2.20.0; extra == "dev"
Provides-Extra: docs
Requires-Dist: sphinx>=4.0.0; extra == "docs"
Requires-Dist: sphinx-rtd-theme>=1.0.0; extra == "docs"
Requires-Dist: myst-parser>=0.18.0; extra == "docs"
Provides-Extra: examples
Requires-Dist: rich>=12.0.0; extra == "examples"
Requires-Dist: click>=8.0.0; extra == "examples"
Dynamic: license-file
